peks/PEKS.py
peks/_init_.py
peks-0.1.dist-info/METADATA
peks-0.1.dist-info/WHEEL
peks-0.1.dist-info/top_level.txt
peks-0.1.dist-info/RECORD
