Metadata-Version: 2.1
Name: peks
Version: 0.1
Summary: PEKS
Home-page: UNKNOWN
Author: UNKNOWN
Author-email: UNKNOWN
License: UNKNOWN
Platform: UNKNOWN
